{"kind":"identitytoolkit#DownloadAccountResponse","users":[{"localId":"JWVcujwxcOfUlccghKYxFtx1oR1x","createdAt":"1742521357379","lastLoginAt":"1744044338058","displayName":"Grass Algae","photoUrl":"https://static.vecteezy.com/system/resources/previews/005/544/718/non_2x/profile-icon-design-free-vector.jpg","providerUserInfo":[{"providerId":"google.com","rawId":"2018460295534941541092846872101885055507","federatedId":"2018460295534941541092846872101885055507","displayName":"Grass Algae","photoUrl":"https://static.vecteezy.com/system/resources/previews/005/544/718/non_2x/profile-icon-design-free-vector.jpg","email":"grass.algae.583@example.com","screenName":"algae_grass"}],"validSince":"1744642218","email":"grass.algae.583@example.com","emailVerified":true,"disabled":false},{"localId":"Qju7Rno1tCCwehU35dlKjEart9gR","createdAt":"1744051091582","lastLoginAt":"1744642228619","displayName":"Uno Uno","providerUserInfo":[{"providerId":"google.com","rawId":"3212967243592822467739387491382077307790","federatedId":"3212967243592822467739387491382077307790","displayName":"Uno Uno","email":"uno@uno.com"}],"validSince":"1744642218","email":"uno@uno.com","emailVerified":true,"disabled":false,"lastRefreshAt":"2025-04-14T15:45:29.034Z"},{"localId":"TqH0azexrDfuAylUfTZUhfYyvu9q","createdAt":"1744051105029","lastLoginAt":"1744051105030","displayName":"Dos Dos","providerUserInfo":[{"providerId":"google.com","rawId":"7730847088089200583722747607910653121870","federatedId":"7730847088089200583722747607910653121870","displayName":"Dos Dos","email":"dos@dos.com"}],"validSince":"1744642218","email":"dos@dos.com","emailVerified":true,"disabled":false},{"localId":"ifRJnVKDl2wXZTZEJxUxoW6HBQIH","createdAt":"1742519964419","lastLoginAt":"1744051075080","displayName":"Olive Raccoon","photoUrl":"https://yca.org.ar/wp-content/uploads/sites/4/2019/06/perfil-avatar-hombre-icono-redondo_24640-14044-300x300.jpg","providerUserInfo":[{"providerId":"google.com","rawId":"3178857832567434122097680898998304292550","federatedId":"3178857832567434122097680898998304292550","displayName":"Olive Raccoon","photoUrl":"https://yca.org.ar/wp-content/uploads/sites/4/2019/06/perfil-avatar-hombre-icono-redondo_24640-14044-300x300.jpg","email":"olive.raccoon.411@example.com","screenName":"raccoon_olive"}],"validSince":"1744642218","email":"olive.raccoon.411@example.com","emailVerified":true,"disabled":false}]}